setup.py
source/__init__.py
source/hookspec.py
source/implementation.py
sslack_cli.egg-info/PKG-INFO
sslack_cli.egg-info/SOURCES.txt
sslack_cli.egg-info/dependency_links.txt
sslack_cli.egg-info/entry_points.txt
sslack_cli.egg-info/not-zip-safe
sslack_cli.egg-info/requires.txt
sslack_cli.egg-info/top_level.txt