Metadata-Version: 1.0
Name: sslack-cli
Version: 0.1.1
Summary: Plugin that gives sslack applications cli feature.
Home-page: UNKNOWN
Author: magniff
Author-email: tinysnippest@gmail.com
License: MIT license
Platform: unix
Platform: linux
Platform: osx
Platform: cygwin
Platform: win32
